opics/__init__.py
opics/components.py
opics/globals.py
opics/network.py
opics/sparam_ops.py
opics/utils.py
opics/libraries/__init__.py
opics/libraries/catalogue.yaml
opics/libraries/catalogue_mgmt.py
tests/__init__.py
tests/test_components.py
tests/test_globals.py
tests/test_read_netlist.py
tests/test_components/test_properties_components_BDC_.csv
tests/test_components/test_properties_components_DC_halfring_.csv
tests/test_components/test_properties_components_GC_.csv
tests/test_components/test_properties_components_Switch_.csv
tests/test_components/test_properties_components_TunableWG_.csv
tests/test_components/test_properties_components_Waveguide_.csv
tests/test_components/test_properties_components_Y_.csv
opics-0.3.3.dist-info/LICENSE
opics-0.3.3.dist-info/METADATA
opics-0.3.3.dist-info/WHEEL
opics-0.3.3.dist-info/top_level.txt
opics-0.3.3.dist-info/RECORD
