Metadata-Version: 2.1
Name: opics
Version: 0.3.3
Summary: Open-source frequency domain circuit simulator for photonic integrated circuits.
Home-page: https://github.com/jaspreetj/opics
Author: Jaspreet Jhoja
Author-email: jaspreet@siepic.com
License: MIT license
Keywords: opics
Platform: UNKNOWN
Classifier: Development Status :: 2 - Pre-Alpha
Classifier: Intended Audience :: Developers
Classifier: License :: OSI Approved :: MIT License
Classifier: Natural Language :: English
Classifier: Programming Language :: Python :: 3
Classifier: Programming Language :: Python :: 3.6
Classifier: Programming Language :: Python :: 3.7
Classifier: Programming Language :: Python :: 3.8
Requires-Python: >=3.6
Requires-Dist: numpy (>=1.19.2)
Requires-Dist: scipy (>=1.5.2)
Requires-Dist: matplotlib (>=3.3.2)
Requires-Dist: pyyaml (>=3.13)
Requires-Dist: holoviews (>=1.14.3)
